GaborNet/GaborLayer.py
GaborNet/__init__.py
GaborNet/tests/__init__.py
GaborNet/tests/test_gabor_net.py
gabornet-0.2.0.dist-info/LICENSE
gabornet-0.2.0.dist-info/WHEEL
gabornet-0.2.0.dist-info/METADATA
gabornet-0.2.0.dist-info/RECORD
