Metadata-Version: 2.1
Name: gabornet
Version: 0.2.0
Summary: Meet Gabor Layer
Home-page: https://github.com/iKintosh/GaborNet
License: MIT
Author: an.alekseev
Author-email: alekseev.as@phystech.edu
Requires-Python: >=3.6.1,<4.0.0
Classifier: Development Status :: 4 - Beta
Classifier: Environment :: GPU :: NVIDIA CUDA :: 10.2
Classifier: Intended Audience :: Education
Classifier: Intended Audience :: Science/Research
Classifier: License :: OSI Approved :: MIT License
Classifier: Operating System :: Unix
Classifier: Programming Language :: Python :: 3
Classifier: Programming Language :: Python :: 3.7
Classifier: Programming Language :: Python :: 3.8
Classifier: Topic :: Scientific/Engineering :: Artificial Intelligence
Classifier: Topic :: Software Development :: Libraries :: Python Modules
Requires-Dist: numpy (>=1.19.1,<2.0.0)
Requires-Dist: torch (>=1.6.0,<2.0.0)
Requires-Dist: torchvision (>=0.7.0,<0.8.0)
Project-URL: Repository, https://github.com/iKintosh/GaborNet
